MANIFEST.in
README.md
requirements.txt
setup.py
fluffy/__init__.py
fluffy/addressbook.py
fluffy/application.py
fluffy/chains.py
fluffy/checks.py
fluffy/default_settings.py
fluffy/dev.py
fluffy/exceptions.py
fluffy/fluffy.py
fluffy/interfaces.py
fluffy/rules.py
fluffy/services.py
fluffy/sessions.py
fluffy/utils.py
fluffy/version.py
fluffy/iptables/chain.jinja
fluffy/iptables/flush.jinja
fluffy/iptables/header.jinja
fluffy/iptables/rule.jinja
fluffy/templates/index.html
fluffy/views/__init__.py
fluffy/views/common.py
fluffy/views/v1/__init__.py
fluffy/views/v1/apidocs/addressbook.yaml
fluffy/views/v1/apidocs/addressbook_get.yaml
fluffy/views/v1/apidocs/chain_get.yaml
fluffy/views/v1/apidocs/chains.yaml
fluffy/views/v1/apidocs/check_get.yaml
fluffy/views/v1/apidocs/checks.yaml
fluffy/views/v1/apidocs/interface_get.yaml
fluffy/views/v1/apidocs/interfaces.yaml
fluffy/views/v1/apidocs/rule_get.yaml
fluffy/views/v1/apidocs/rules.yaml
fluffy/views/v1/apidocs/service_get.yaml
fluffy/views/v1/apidocs/services.yaml
fluffy/views/v1/apidocs/session_add.yaml
fluffy/views/v1/apidocs/session_addressbook.yaml
fluffy/views/v1/apidocs/session_addressbook_add.yaml
fluffy/views/v1/apidocs/session_addressbook_delete.yaml
fluffy/views/v1/apidocs/session_addressbook_get.yaml
fluffy/views/v1/apidocs/session_addressbook_update.yaml
fluffy/views/v1/apidocs/session_chain_add.yaml
fluffy/views/v1/apidocs/session_chain_delete.yaml
fluffy/views/v1/apidocs/session_chain_get.yaml
fluffy/views/v1/apidocs/session_chain_update.yaml
fluffy/views/v1/apidocs/session_chains.yaml
fluffy/views/v1/apidocs/session_check_add.yaml
fluffy/views/v1/apidocs/session_check_delete.yaml
fluffy/views/v1/apidocs/session_check_get.yaml
fluffy/views/v1/apidocs/session_check_update.yaml
fluffy/views/v1/apidocs/session_checks.yaml
fluffy/views/v1/apidocs/session_commit.yaml
fluffy/views/v1/apidocs/session_confirm.yaml
fluffy/views/v1/apidocs/session_delete.yaml
fluffy/views/v1/apidocs/session_get.yaml
pyfluffy.egg-info/PKG-INFO
pyfluffy.egg-info/SOURCES.txt
pyfluffy.egg-info/dependency_links.txt
pyfluffy.egg-info/entry_points.txt
pyfluffy.egg-info/pbr.json
pyfluffy.egg-info/requires.txt
pyfluffy.egg-info/top_level.txt