Metadata-Version: 1.1
Name: pyfluffy
Version: 0.0.11
Summary: Fluffy - A Firewall as a Service
Home-page: https://github.com/m4ce/fluffy
Author: Matteo Cerutti
Author-email: matteo.cerutti@hotmail.co.uk
License: Apache License 2.0
Keywords: firewall,fwaas,firewall as a service,iptables as a service
Platform: UNKNOWN
Classifier: Development Status :: 3 - Alpha
Classifier: Environment :: Console
Classifier: Framework :: Flask
Classifier: Intended Audience :: Information Technology
Classifier: Intended Audience :: System Administrators
Classifier: Intended Audience :: Telecommunications Industry
Classifier: License :: OSI Approved :: Apache Software License
Classifier: Operating System :: POSIX :: Linux
Classifier: Programming Language :: Python :: 2.7
Classifier: Topic :: Security
Classifier: Topic :: System :: Networking :: Firewalls
